tooldev/__init__.py
tooldev/cli_utils.py
tooldev/directory_utils.py
tooldev/namespace_utils.py
tooldev/commands/__init__.py
tooldev/commands/lsp_command.py
tooldev/commands/pwp_command.py
tooldev/commands/root_command.py
tooldev/commands/shell_command.py
tooldev-0.1.1.dist-info/entry_points.txt
tooldev-0.1.1.dist-info/WHEEL
tooldev-0.1.1.dist-info/METADATA
tooldev-0.1.1.dist-info/RECORD
