Metadata-Version: 2.1
Name: tooldev
Version: 0.1.1
Summary: tooldev is a suite of cli tools for performing python development
Requires-Python: >=3.7
Requires-Dist: typing-extensions >=4.2.0, <5
Requires-Dist: toolcli >=0.6.6, <0.7
Requires-Dist: toolstr >=0.7.4, <0.8
Requires-Dist: tuna >=0.5.11, <0.6.0
